tdameritrade_api/__init__.py
tdameritrade_api/abstract_auth.py
tdameritrade_api/api.py
tdameritrade_api/auth.py
tdameritrade_api/helpers.py
tdameritrade_api/test.py
tdameritrade_api/token_manager.py
tdameritrade_api-0.0.2.dist-info/LICENSE
tdameritrade_api-0.0.2.dist-info/METADATA
tdameritrade_api-0.0.2.dist-info/WHEEL
tdameritrade_api-0.0.2.dist-info/top_level.txt
tdameritrade_api-0.0.2.dist-info/RECORD
